linkcovery/__init__.py
linkcovery/cli/__init__.py
linkcovery/cli/config.py
linkcovery/cli/data.py
linkcovery/cli/links.py
linkcovery/core/__init__.py
linkcovery/core/config.py
linkcovery/core/database.py
linkcovery/core/exceptions.py
linkcovery/core/models.py
linkcovery/core/utils.py
linkcovery/services/__init__.py
linkcovery/services/data_service.py
linkcovery/services/link_service.py
linkcovery-1.7.8.dist-info/METADATA
linkcovery-1.7.8.dist-info/WHEEL
linkcovery-1.7.8.dist-info/entry_points.txt
linkcovery-1.7.8.dist-info/licenses/LICENSE
linkcovery-1.7.8.dist-info/RECORD
