Metadata-Version: 2.4
Name: linkcovery
Version: 1.7.8
Summary: A modern, fast, and intuitive bookmark management CLI tool
Project-URL: Homepage, https://github.com/arian24b/linkcovery
Project-URL: Issues, https://github.com/arian24b/linkcovery/issues
Project-URL: Changelog, https://github.com/arian24b/linkcovery/blob/main/CHANGELOG.md
Project-URL: Documentation, https://github.com/arian24b/linkcovery#readme
Author-email: Arian Omrani <arian24b@gmail.com>
Maintainer-email: Arian Omrani <arian24b@gmail.com>
License-Expression: MIT
License-File: LICENSE
Keywords: bookmark,cli,link,management,python
Requires-Python: >=3.13
Requires-Dist: beautifulsoup4>=4.13.4
Requires-Dist: httpx[http2]>=0.28.1
Requires-Dist: platformdirs>=4.3.8
Requires-Dist: pydantic>=2.10.0
Requires-Dist: sqlalchemy>=2.0.38
Requires-Dist: typer>=0.16.1
